payjp/__init__.py
payjp/api_requestor.py
payjp/error.py
payjp/example.py
payjp/http_client.py
payjp/resource.py
payjp/version.py
payjp/test/__init__.py
payjp/test/helper.py
payjp/test/test_http_client.py
payjp/test/test_integration.py
payjp/test/test_requestor.py
payjp/test/test_resources.py
payjp-1.6.1.dist-info/licenses/LICENSE
payjp-1.6.1.dist-info/METADATA
payjp-1.6.1.dist-info/WHEEL
payjp-1.6.1.dist-info/top_level.txt
payjp-1.6.1.dist-info/RECORD
